[
{"timestamp":"2025-06-01T19:19:29Z","killer_uid":"a1ea9e75-567f-47af-be3f-e803062c96dc","killer_name":"Robzd","killer_faction":"SCR_CampaignFaction<0x0000022DBC4F28D0>","action":"suicide","victim_uid":"a1ea9e75-567f-47af-be3f-e803062c96dc","victim_name":"Robzd","victim_faction":"SCR_CampaignFaction<0x0000022DBC4F28D0>"}
,
{"timestamp":"2025-06-01T19:20:00Z","killer_uid":"2e042239-4f37-4371-8f54-ddb9128fe76c","killer_name":"Youngblood","killer_faction":"SCR_CampaignFaction<0x0000022DBC4F28D0>","action":"teamkill","victim_uid":"04493d67-cb5a-4b50-a767-910bf28d696e","victim_name":"I Zesk45 I","victim_faction":"SCR_CampaignFaction<0x0000022DBC4F28D0>"}
,
{"timestamp":"2025-06-01T19:20:49Z","killer_uid":"6a512207-c48c-496f-9e91-7f6cc399df4f","killer_name":"Depth.Charge","killer_faction":"SCR_CampaignFaction<0x0000022DBC4F28D0>","action":"suicide","victim_uid":"6a512207-c48c-496f-9e91-7f6cc399df4f","victim_name":"Depth.Charge","victim_faction":"SCR_CampaignFaction<0x0000022DBC4F28D0>"}
,
{"timestamp":"2025-06-01T19:21:45Z","killer_uid":"2e30f153-fea9-4c16-9add-81cb4ec0e0c9","killer_name":"Sey_Kono","killer_faction":"SCR_CampaignFaction<0x0000022DBC4F2730>","action":"suicide","victim_uid":"2e30f153-fea9-4c16-9add-81cb4ec0e0c9","victim_name":"Sey_Kono","victim_faction":"SCR_CampaignFaction<0x0000022DBC4F2730>"}
,
{"timestamp":"2025-06-01T19:22:52Z","killer_uid":"6d8e6260-5c34-4a6e-bb84-81a5ae014af6","killer_name":"JJflakey2002","killer_faction":"SCR_CampaignFaction<0x0000022DBC4F28D0>","action":"teamkill","victim_uid":"11818995-8543-4904-8f73-bcc4e4f3a8e9","victim_name":"Marcus_Buch","victim_faction":"SCR_CampaignFaction<0x0000022DBC4F28D0>"}
,
{"timestamp":"2025-06-01T19:22:52Z","killer_uid":"6d8e6260-5c34-4a6e-bb84-81a5ae014af6","killer_name":"JJflakey2002","killer_faction":"SCR_CampaignFaction<0x0000022DBC4F28D0>","action":"suicide","victim_uid":"6d8e6260-5c34-4a6e-bb84-81a5ae014af6","victim_name":"JJflakey2002","victim_faction":"SCR_CampaignFaction<0x0000022DBC4F28D0>"}
,
{"timestamp":"2025-06-01T19:23:28Z","killer_uid":"101f97b0-15f9-4226-bf64-3fbacc4b10f8","killer_name":"Dark De'mora","killer_faction":"SCR_CampaignFaction<0x0000022DBC4F28D0>","action":"suicide","victim_uid":"101f97b0-15f9-4226-bf64-3fbacc4b10f8","victim_name":"Dark De'mora","victim_faction":"SCR_CampaignFaction<0x0000022DBC4F28D0>"}
,
{"timestamp":"2025-06-01T19:23:56Z","killer_uid":"04493d67-cb5a-4b50-a767-910bf28d696e","killer_name":"I Zesk45 I","killer_faction":"SCR_CampaignFaction<0x0000022DBC4F28D0>","action":"suicide","victim_uid":"04493d67-cb5a-4b50-a767-910bf28d696e","victim_name":"I Zesk45 I","victim_faction":"SCR_CampaignFaction<0x0000022DBC4F28D0>"}
